tracnav/.gitignore
tracnav/__init__.py
tracnav/tracnav.py
tracnav/htdocs/css/tracnav.css
TracNav-4.3.dist-info/COPYING
TracNav-4.3.dist-info/METADATA
TracNav-4.3.dist-info/WHEEL
TracNav-4.3.dist-info/entry_points.txt
TracNav-4.3.dist-info/top_level.txt
TracNav-4.3.dist-info/RECORD
