Metadata-Version: 2.1
Name: TracNav
Version: 4.3
Summary: The Navigation Bar for Trac
Home-page: https://svn.ipd.kit.edu/trac/javaparty/wiki/TracNav
Author: Bernhard Haumacher
Author-email: haui@haumacher.de
Maintainer: Thomas Moschny
Maintainer-email: thomas.moschny@gmx.de
License: GPLv2+
Download-URL: https://svn.ipd.kit.edu/trac/javaparty/wiki/TracNav/DownloadAndInstall
Project-URL: Source Code, https://github.com/thmo/tracnav
Keywords: trac,toc,plugin
Platform: UNKNOWN
Classifier: Development Status :: 5 - Production/Stable
Classifier: Environment :: Web Environment
Classifier: Framework :: Trac
Classifier: Intended Audience :: System Administrators
Classifier: License :: OSI Approved :: GNU General Public License (GPL)
Classifier: Operating System :: OS Independent
Classifier: Programming Language :: Python
Classifier: Topic :: Internet :: WWW/HTTP :: Dynamic Content
